toolsvanwinkel-0.0.1.data/data/etc/jupyter/nbconfig/notebook.d/writefile.json
toolsvanwinkel-0.0.1.data/data/share/jupyter/nbextensions/writefile/main.js
toolsvanwinkel-0.0.1.data/data/share/jupyter/nbextensions/writefile/writefile.yaml
writefile/__init__.py
writefile/static/main.js
writefile/static/writefile.yaml
toolsvanwinkel-0.0.1.dist-info/METADATA
toolsvanwinkel-0.0.1.dist-info/WHEEL
toolsvanwinkel-0.0.1.dist-info/top_level.txt
toolsvanwinkel-0.0.1.dist-info/RECORD
