Metadata-Version: 2.1
Name: toolsvanwinkel
Version: 0.0.1
Summary: Some tools including extensions for Jupyter notebooks.
Author: Jens Vanwinkel
Author-email: jensvanwinkel@hotmail.be
Requires-Dist: notebook (>=5.3)
Requires-Dist: jupyter-contrib-nbextensions
Requires-Dist: widgetsnbextension
